<?xml version="1.0"?>
<!DOCTYPE program SYSTEM "/home/pfeautri/Syntol/Doc/improg.dtd">
<program label="counterex1a">
  <declaration>
    <inside> counterex1a </inside>
    <identifier> nondet </identifier>
    <function>
      <identifier> nondet </identifier>
      <basic size="32"> __integer</basic>
    </function>
  </declaration>
  <declaration>
    <inside> counterex1a </inside>
    <identifier> counterex1a </identifier>
    <function>
      <identifier> counterex1a </identifier>
      <basic size="32"> __integer</basic>
      <identifier> n </identifier>
      <basic size="32"> __integer</basic>
      <identifier> b </identifier>
      <basic size="32"> __integer</basic>
      <identifier> x </identifier>
      <basic size="32"> __integer</basic>
      <identifier> y </identifier>
      <basic size="32"> __integer</basic>
    </function>
  </declaration>
  <fundef label="counterex1a"/>
  <while label="lbl_1">
    <expression>
      <operator>  __conjunction  </operator>
      <expression>
        <operator>  __conjunction  </operator>
        <expression>
          <operator>  __ge  </operator>
          <expression>
            <identifier> x </identifier>
          </expression>
          <expression>
            <constant> cst__2 </constant>
          </expression>
        </expression>
        <expression>
          <operator>  __le  </operator>
          <expression>
            <constant> cst__2 </constant>
          </expression>
          <expression>
            <identifier> y </identifier>
          </expression>
        </expression>
      </expression>
      <expression>
        <operator>  __le  </operator>
        <expression>
          <identifier> y </identifier>
        </expression>
        <expression>
          <identifier> n </identifier>
        </expression>
      </expression>
    </expression>
  </while>
  <if label="lbl_3">
    <expression>
      <operator>  __eq  </operator>
      <expression>
        <identifier> b </identifier>
      </expression>
      <expression>
        <constant> cst__2 </constant>
      </expression>
    </expression>
  </if>
  <if label="lbl_5">
    <expression>
      <operator>  __gt  </operator>
      <expression>
        <operator> __funcall </operator>
        <expression>
          <identifier> nondet </identifier>
        </expression>
      </expression>
      <expression>
        <constant> cst__2 </constant>
      </expression>
    </expression>
  </if>
  <if label="lbl_10">
    <expression>
      <operator>  __gt  </operator>
      <expression>
        <operator> __funcall </operator>
        <expression>
          <identifier> nondet </identifier>
        </expression>
      </expression>
      <expression>
        <constant> cst__2 </constant>
      </expression>
    </expression>
  </if>
  <statement label="lbl_4">
    <inside> counterex1a counterex1a lbl_1 lbl_3 _true </inside>
    <expression>
      <operator> _post_incr </operator>
      <expression>
        <identifier> y </identifier>
      </expression>
    </expression>
  </statement>
  <statement label="lbl_7">
    <inside> counterex1a counterex1a lbl_1 lbl_3 _true lbl_5 _true </inside>
    <expression>
      <operator>  __assignment  </operator>
      <expression>
        <identifier> b </identifier>
      </expression>
      <expression>
        <constant> cst__6 </constant>
      </expression>
    </expression>
  </statement>
  <statement label="lbl_8">
    <inside> counterex1a counterex1a lbl_1 lbl_3 _true lbl_5 _false </inside>
    <nop/>
  </statement>
  <statement label="lbl_9">
    <inside> counterex1a counterex1a lbl_1 lbl_3 _false </inside>
    <expression>
      <operator> _post_decr </operator>
      <expression>
        <identifier> y </identifier>
      </expression>
    </expression>
  </statement>
  <statement label="lbl_11">
    <inside> counterex1a counterex1a lbl_1 lbl_3 _false lbl_10 _true </inside>
    <expression>
      <operator> _post_decr </operator>
      <expression>
        <identifier> x </identifier>
      </expression>
    </expression>
  </statement>
  <statement label="lbl_12">
    <inside> counterex1a counterex1a lbl_1 lbl_3 _false lbl_10 _true </inside>
    <expression>
      <operator>  __assignment  </operator>
      <expression>
        <identifier> b </identifier>
      </expression>
      <expression>
        <constant> cst__2 </constant>
      </expression>
    </expression>
  </statement>
  <statement label="lbl_13">
    <inside> counterex1a counterex1a lbl_1 lbl_3 _false lbl_10 _false </inside>
    <nop/>
  </statement>
  <statement label="lbl_14">
    <inside> counterex1a counterex1a </inside>
    <return>    </return>
  </statement>
  <declaration>
    <inside> counterex1a </inside>
    <constant value="1"> cst__6 </constant>
    <basic> __integer </basic>
  </declaration>
  <declaration>
    <inside> counterex1a </inside>
    <constant value="0"> cst__2 </constant>
    <basic> __integer </basic>
  </declaration>
</program>
