<?xml version="1.0"?>
<!DOCTYPE program SYSTEM "/home/pfeautri/Syntol/Doc/improg.dtd">
<program label="wcet0">
  <declaration>
    <inside> wcet0 </inside>
    <identifier> nondet </identifier>
    <function>
      <identifier> nondet </identifier>
      <basic size="32"> __integer</basic>
    </function>
  </declaration>
  <declaration>
    <inside> wcet0 </inside>
    <identifier> wcet0 </identifier>
    <function>
      <identifier> wcet0 </identifier>
      <basic size="32"> __integer</basic>
      <identifier> n </identifier>
      <basic size="32"> __integer</basic>
    </function>
  </declaration>
  <declaration>
    <inside> wcet0 wcet0 </inside>
    <identifier> i </identifier>
    <basic size="32"> __integer</basic>
  </declaration>
  <declaration>
    <inside> wcet0 wcet0 </inside>
    <identifier> j </identifier>
    <basic size="32"> __integer</basic>
  </declaration>
  <fundef label="wcet0"/>
  <if label="lbl_4">
    <expression>
      <operator>  __ge  </operator>
      <expression>
        <identifier> n </identifier>
      </expression>
      <expression>
        <constant> cst__5 </constant>
      </expression>
    </expression>
  </if>
  <doWhile label="lbl_6">
    <expression>
      <operator>  __gt  </operator>
      <expression>
        <identifier> i </identifier>
      </expression>
      <expression>
        <constant> cst__1 </constant>
      </expression>
    </expression>
  </doWhile>
  <if label="lbl_7">
    <expression>
      <operator>  __gt  </operator>
      <expression>
        <operator> __funcall </operator>
        <expression>
          <identifier> nondet </identifier>
        </expression>
      </expression>
      <expression>
        <constant> cst__1 </constant>
      </expression>
    </expression>
  </if>
  <if label="lbl_9">
    <expression>
      <operator>  __ge  </operator>
      <expression>
        <identifier> j </identifier>
      </expression>
      <expression>
        <identifier> n </identifier>
      </expression>
    </expression>
  </if>
  <if label="lbl_13">
    <expression>
      <operator>  __le  </operator>
      <expression>
        <identifier> j </identifier>
      </expression>
      <expression>
        <operator> __subtraction </operator>
        <expression>
          <identifier> n </identifier>
        </expression>
      </expression>
    </expression>
  </if>
  <statement label="lbl_2">
    <inside> wcet0 wcet0 </inside>
    <expression>
      <operator>  __assignment  </operator>
      <expression>
        <identifier> j </identifier>
      </expression>
      <expression>
        <constant> cst__1 </constant>
      </expression>
    </expression>
  </statement>
  <statement label="lbl_3">
    <inside> wcet0 wcet0 </inside>
    <expression>
      <operator>  __assignment  </operator>
      <expression>
        <identifier> i </identifier>
      </expression>
      <expression>
        <identifier> n </identifier>
      </expression>
    </expression>
  </statement>
  <statement label="lbl_8">
    <inside> wcet0 wcet0 lbl_4 _true lbl_6 lbl_7 _true </inside>
    <expression>
      <operator> _post_incr </operator>
      <expression>
        <identifier> j </identifier>
      </expression>
    </expression>
  </statement>
  <statement label="lbl_10">
    <inside> wcet0 wcet0 lbl_4 _true lbl_6 lbl_7 _true lbl_9 _true </inside>
    <expression>
      <operator>  __assignment  </operator>
      <expression>
        <identifier> j </identifier>
      </expression>
      <expression>
        <constant> cst__1 </constant>
      </expression>
    </expression>
  </statement>
  <statement label="lbl_11">
    <inside> wcet0 wcet0 lbl_4 _true lbl_6 lbl_7 _true lbl_9 _false </inside>
    <nop/>
  </statement>
  <statement label="lbl_12">
    <inside> wcet0 wcet0 lbl_4 _true lbl_6 lbl_7 _false </inside>
    <expression>
      <operator> _post_decr </operator>
      <expression>
        <identifier> j </identifier>
      </expression>
    </expression>
  </statement>
  <statement label="lbl_14">
    <inside> wcet0 wcet0 lbl_4 _true lbl_6 lbl_7 _false lbl_13 _true </inside>
    <expression>
      <operator>  __assignment  </operator>
      <expression>
        <identifier> j </identifier>
      </expression>
      <expression>
        <constant> cst__1 </constant>
      </expression>
    </expression>
  </statement>
  <statement label="lbl_15">
    <inside> wcet0 wcet0 lbl_4 _true lbl_6 lbl_7 _false lbl_13 _false </inside>
    <nop/>
  </statement>
  <statement label="lbl_16">
    <inside> wcet0 wcet0 lbl_4 _true lbl_6 </inside>
    <expression>
      <operator> _post_decr </operator>
      <expression>
        <identifier> i </identifier>
      </expression>
    </expression>
  </statement>
  <statement label="lbl_17">
    <inside> wcet0 wcet0 lbl_4 _false </inside>
    <nop/>
  </statement>
  <statement label="lbl_18">
    <inside> wcet0 wcet0 </inside>
    <return>    </return>
  </statement>
  <declaration>
    <inside> wcet0 </inside>
    <constant value="1"> cst__5 </constant>
    <basic> __integer </basic>
  </declaration>
  <declaration>
    <inside> wcet0 </inside>
    <constant value="0"> cst__1 </constant>
    <basic> __integer </basic>
  </declaration>
</program>
